utsc/__main__.py
utsc-0.0.3.dist-info/entry_points.txt
utsc-0.0.3.dist-info/LICENSE
utsc-0.0.3.dist-info/WHEEL
utsc-0.0.3.dist-info/METADATA
utsc-0.0.3.dist-info/RECORD
